Workbook

Sheet 2023
A1: id | B1: empresa_tic | C1: ano_tri | D1: data_ini | E1: data_fim | F1: conta | G1: descricao | H1: valor | I1: tipo_balanco
A2: 5625085 | B2: ALPA | C2: 20234T | D2: 45291 | E2: 45291 | F2: 1 | G2: Ativo Total | H2: 6327389 | I2: DFs Consolidadas
A3: 5625086 | B3: ALPA | C3: 20234T | D3: 45291 | E3: 45291 | F3: 1.01 | G3: Ativo Circulante | H3: 3199595 | I3: DFs Consolidadas
A4: 5625087 | B4: ALPA | C4: 20234T | D4: 45291 | E4: 45291 | F4: 1.01.01 | G4: Caixa e Equivalentes de Caixa | H4: 922525 | I4: DFs Consolidadas
A5: 5625088 | B5: ALPA | C5: 20234T | D5: 45291 | E5: 45291 | F5: 1.01.02 | G5: Aplicações Financeiras | H5: 0 | I5: DFs Consolidadas
A6: 5625089 | B6: ALPA | C6: 20234T | D6: 45291 | E6: 45291 | F6: 1.01.02.01 | G6: Aplicações Financeiras Avaliadas a Valor Justo através do Resultado | H6: 0 | I6: DFs Consolidadas
A7: 5625090 | B7: ALPA | C7: 20234T | D7: 45291 | E7: 45291 | F7: 1.01.02.01.01 | G7: Títulos para Negociação | H7: 0 | I7: DFs Consolidadas
A8: 5625091 | B8: ALPA | C8: 20234T | D8: 45291 | E8: 45291 | F8: 1.01.02.01.02 | G8: Títulos Designados a Valor Justo | H8: 0 | I8: DFs Consolidadas
A9: 5625092 | B9: ALPA | C9: 20234T | D9: 45291 | E9: 45291 | F9: 1.01.02.02 | G9: Aplicações Financeiras Avaliadas a Valor Justo através de Outros Resultados Abrangentes | H9: 0 | I9: DFs Consolidadas
A10: 5625093 | B10: ALPA | C10: 20234T | D10: 45291 | E10: 45291 | F10: 1.01.02.03 | G10: Aplicações Financeiras Avaliadas ao Custo Amortizado | H10: 0 | I10: DFs Consolidadas
A11: 5625094 | B11: ALPA | C11: 20234T | D11: 45291 | E11: 45291 | F11: 1.01.03 | G11: Contas a Receber | H11: 883735 | I11: DFs Consolidadas
A12: 5625095 | B12: ALPA | C12: 20234T | D12: 45291 | E12: 45291 | F12: 1.01.03.01 | G12: Clientes | H12: 883735 | I12: DFs Consolidadas
A13: 5625096 | B13: ALPA | C13: 20234T | D13: 45291 | E13: 45291 | F13: 1.01.03.02 | G13: Outras Contas a Receber | H13: 0 | I13: DFs Consolidadas
... A338: 5625421 | B338: ALPA | C338: 20234T | D338: 44927 | E338: 45291 | F338: 7.08.05 | G338: Outros | H338: 0 | I338: DFs Consolidadas

Sheet 2024
A1: id | B1: empresa_tic | C1: ano_tri | D1: data_ini | E1: data_fim | F1: conta | G1: descricao | H1: valor | I1: tipo_balanco
A2: 6134452 | B2: ALPA | C2: 20244T | D2: 45657 | E2: 45657 | F2: 1 | G2: Ativo Total | H2: 6839725 | I2: DFs Consolidadas
A3: 6134453 | B3: ALPA | C3: 20244T | D3: 45657 | E3: 45657 | F3: 1.01 | G3: Ativo Circulante | H3: 3459140 | I3: DFs Consolidadas
A4: 6134454 | B4: ALPA | C4: 20244T | D4: 45657 | E4: 45657 | F4: 1.01.01 | G4: Caixa e Equivalentes de Caixa | H4: 1488511 | I4: DFs Consolidadas
A5: 6134455 | B5: ALPA | C5: 20244T | D5: 45657 | E5: 45657 | F5: 1.01.02 | G5: Aplicações Financeiras | H5: 0 | I5: DFs Consolidadas
A6: 6134456 | B6: ALPA | C6: 20244T | D6: 45657 | E6: 45657 | F6: 1.01.02.01 | G6: Aplicações Financeiras Avaliadas a Valor Justo através do Resultado | H6: 0 | I6: DFs Consolidadas
A7: 6134457 | B7: ALPA | C7: 20244T | D7: 45657 | E7: 45657 | F7: 1.01.02.01.01 | G7: Títulos para Negociação | H7: 0 | I7: DFs Consolidadas
A8: 6134458 | B8: ALPA | C8: 20244T | D8: 45657 | E8: 45657 | F8: 1.01.02.01.02 | G8: Títulos Designados a Valor Justo | H8: 0 | I8: DFs Consolidadas
A9: 6134459 | B9: ALPA | C9: 20244T | D9: 45657 | E9: 45657 | F9: 1.01.02.02 | G9: Aplicações Financeiras Avaliadas a Valor Justo através de Outros Resultados Abrangentes | H9: 0 | I9: DFs Consolidadas
A10: 6134460 | B10: ALPA | C10: 20244T | D10: 45657 | E10: 45657 | F10: 1.01.02.03 | G10: Aplicações Financeiras Avaliadas ao Custo Amortizado | H10: 0 | I10: DFs Consolidadas
A11: 6134461 | B11: ALPA | C11: 20244T | D11: 45657 | E11: 45657 | F11: 1.01.03 | G11: Contas a Receber | H11: 997875 | I11: DFs Consolidadas
A12: 6134462 | B12: ALPA | C12: 20244T | D12: 45657 | E12: 45657 | F12: 1.01.03.01 | G12: Clientes | H12: 0 | I12: DFs Consolidadas
A13: 6134463 | B13: ALPA | C13: 20244T | D13: 45657 | E13: 45657 | F13: 1.01.03.02 | G13: Outras Contas a Receber | H13: 0 | I13: DFs Consolidadas
... A313: 6134763 | B313: ALPA | C313: 20244T | D313: 45292 | E313: 45657 | F313: 7.08.05 | G313: Outros | H313: 0 | I313: DFs Consolidadas

Sheet 2025
A1: id | B1: empresa_tic | C1: ano_tri | D1: data_ini | E1: data_fim | F1: conta | G1: descricao | H1: valor | I1: tipo_balanco
A2: 6532991 | B2: ALPA | C2: 20254T | D2: 46022 | E2: 46022 | F2: 1 | G2: Ativo Total | H2: 6096758 | I2: DFs Consolidadas
A3: 6532992 | B3: ALPA | C3: 20254T | D3: 46022 | E3: 46022 | F3: 1.01 | G3: Ativo Circulante | H3: 2711014 | I3: DFs Consolidadas
A4: 6532993 | B4: ALPA | C4: 20254T | D4: 46022 | E4: 46022 | F4: 1.01.01 | G4: Caixa e Equivalentes de Caixa | H4: 555595 | I4: DFs Consolidadas
A5: 6532994 | B5: ALPA | C5: 20254T | D5: 46022 | E5: 46022 | F5: 1.01.02 | G5: Aplicações Financeiras | H5: 0 | I5: DFs Consolidadas
A6: 6532995 | B6: ALPA | C6: 20254T | D6: 46022 | E6: 46022 | F6: 1.01.02.01 | G6: Aplicações Financeiras Avaliadas a Valor Justo através do Resultado | H6: 0 | I6: DFs Consolidadas
A7: 6532996 | B7: ALPA | C7: 20254T | D7: 46022 | E7: 46022 | F7: 1.01.02.01.01 | G7: Títulos para Negociação | H7: 0 | I7: DFs Consolidadas
A8: 6532997 | B8: ALPA | C8: 20254T | D8: 46022 | E8: 46022 | F8: 1.01.02.01.02 | G8: Títulos Designados a Valor Justo | H8: 0 | I8: DFs Consolidadas
A9: 6532998 | B9: ALPA | C9: 20254T | D9: 46022 | E9: 46022 | F9: 1.01.02.02 | G9: Aplicações Financeiras Avaliadas a Valor Justo através de Outros Resultados Abrangentes | H9: 0 | I9: DFs Consolidadas
A10: 6532999 | B10: ALPA | C10: 20254T | D10: 46022 | E10: 46022 | F10: 1.01.02.03 | G10: Aplicações Financeiras Avaliadas ao Custo Amortizado | H10: 0 | I10: DFs Consolidadas
A11: 6533000 | B11: ALPA | C11: 20254T | D11: 46022 | E11: 46022 | F11: 1.01.03 | G11: Contas a Receber | H11: 1189571 | I11: DFs Consolidadas
A12: 6533001 | B12: ALPA | C12: 20254T | D12: 46022 | E12: 46022 | F12: 1.01.03.01 | G12: Clientes | H12: 0 | I12: DFs Consolidadas
A13: 6533002 | B13: ALPA | C13: 20254T | D13: 46022 | E13: 46022 | F13: 1.01.03.02 | G13: Outras Contas a Receber | H13: 0 | I13: DFs Consolidadas
... A314: 6533303 | B314: ALPA | C314: 20254T | D314: 45658 | E314: 46022 | F314: 7.08.05 | G314: Outros | H314: 0 | I314: DFs Consolidadas

Sheet indicadores
A1: Indicadores | B1: 2025 | C1: 2024
A2: Capital Circulante Líquido (AC-PC) | B2: ='2025'!$H$3-'2025'!$H$64 -> 1023931 | C2: ='2024'!$H$3-'2024'!$H$64 -> 2109534
A3: Liquidez Corrente (AC/PC) | B3: ='2025'!$H$3/'2025'!$H$64 -> 1.6069239 | C3: ='2024'!$H$3/'2024'!$H$64 -> 2.563074
A4: Liquidez Seca ((AC-Est-DA)/PC | B4: =('2025'!$H$3-'2025'!$H$14-'2025'!$H$18)/'2025'!$H$64 -> 1.1354272 | C4: =('2024'!$H$3-'2024'!$H$14-'2024'!$H$18)/'2024'!$H$64 -> 2.0032513
A5: Liquidez Absoluta (Caixa e Equiv/PC) | B5: ='2025'!$H$4/'2025'!$H$64 -> 0.32932286 | C5: ='2024'!$H$4/'2024'!$H$64 -> 1.1029226
A6: Liquidez Geral ((AC + ARLP)/(PC + PNC)) | B6: =('2025'!$H$3+'2025'!$H$26)/('2025'!$H$64+'2025'!$H$109) -> 1.1821807 | C6: =('2024'!$H$3+'2024'!$H$26)/('2024'!$H$64+'2024'!$H$108) -> 1.4102572
A7: PME (((EstInic + EstFin)/2)/CMV)x360 | B7: =(('2024'!$H$14+'2025'!$H$14)/2)/ABS('2025'!$H$177)*360 -> 121.13345 | C7: =(('2023'!$H$14+'2024'!$H$14)/2)/ABS('2024'!$H$176)*360 -> 131.53873
A8: Giro de Estoque (360/PME) | B8: =360/B7 -> 2.9719289 | C8: =360/C7 -> 2.7368366
A9: PMRV (((ClientesInic + ClientesFin)/2)/Receita)x360 | B9: =(('2024'!$H$11+'2025'!$H$11)/2)/'2025'!$H$176*360 -> 86.254359 | C9: =(('2023'!$H$11+'2024'!$H$11)/2)/'2024'!$H$175*360 -> 82.440156
A10: Compras | B10: =ABS('2025'!$H$177)+'2025'!$H$14-'2024'!$H$14 -> 2234223 | C10: =ABS('2024'!$H$176)+'2024'!$H$14-'2023'!$H$14 -> 2047054
A11: PMPF (((FornecedorInic + FornecedorFin)/2)/Compras)x360 | B11: =(('2024'!$H$68+'2025'!$H$68)/2)/B10*360 -> 72.318135 | C11: =(('2023'!$H$78+'2024'!$H$68)/2)/C10*360 -> 74.781564
A12: Ciclo Operacional (PME + PMRV) | B12: =B7+B9 -> 207.38781 | C12: =C7+C9 -> 213.97888
A13: Ciclo Financeiro (CO - PMPF) | B13: =B12-B11 -> 135.06967 | C13: =C12-C11 -> 139.19732
A14: Ciclo Econômico (PME) | B14: =B7 -> 121.13345 | C14: =C7 -> 131.53873
A15: Ativo Circulante Financeiro - ACF | B15: ='2025'!$H$4+'2025'!$H$5 -> 555595 | C15: ='2024'!$H$4+'2024'!$H$5 -> 1488511
A16: Ativo Circulante Operacional - ACO | B16: ='2025'!$H$3-B15 -> 2155419 | C16: ='2024'!$H$3-C15 -> 1970629
A17: Ativo Circulante | B17: ='2025'!$H$3 -> 2711014 | C17: ='2024'!$H$3 -> 3459140
A18: Passivo Circulante Financeiro - PCF | B18: ='2025'!$H$76 -> 380547 | C18: ='2024'!$H$76 -> 251373
A19: Passivo Circulante Operacional - PCO | B19: ='2025'!$H$64-B18 -> 1306536 | C19: ='2024'!$H$64-C18 -> 1098233
A20: Passivo Circulante | B20: ='2025'!$H$64 -> 1687083 | C20: ='2024'!$H$64 -> 1349606
A21: Saldo em Tesouraria - ST (ACF-PCF) | B21: =B15-B18 -> 175048 | C21: =C15-C18 -> 1237138
A22: Necessidade de Capital de Giro - NCG (ACO-PCO) | B22: =B16-B19 -> 848883 | C22: =C16-C19 -> 872396
A23: Capital de Giro Líquido - CGL (AC-PC) | B23: ='2025'!$H$3-'2025'!$H$64 -> 1023931 | C23: ='2024'!$H$3-'2024'!$H$64 -> 2109534
A24: Relação de Capitais (Passivo/PL) | B24: =('2025'!$H$64+'2025'!$H$109)/'2025'!$H$150 -> 0.83429605 | C24: =('2024'!$H$64+'2024'!$H$108)/'2024'!$H$149 -> 0.69452001
A25: Endividamento Geral (Passivo/(Passivo + PL)) | B25: =('2025'!$H$64+'2025'!$H$109)/('2025'!$H$64+'2025'!$H$109+'2025'!$H$150) -> 0.45483173 | C25: =('2024'!$H$64+'2024'!$H$108)/('2024'!$H$64+'2024'!$H$108+'2024'!$H$149) -> 0.40986238
A26: Solvência Geral (Ativo/Passivo) | B26: ='2025'!$H$2/('2025'!$H$64+'2025'!$H$109) -> 2.1986153 | C26: ='2024'!$H$2/('2024'!$H$64+'2024'!$H$108) -> 2.4398433
A27: Composição do Endividamento (PC/Passivo) | B27: ='2025'!$H$64/('2025'!$H$64+'2025'!$H$109) -> 0.60839654 | C27: ='2024'!$H$64/('2024'!$H$64+'2024'!$H$108) -> 0.48142684
A28: Imobilização do PL (Ativos Fixos/PL) | B28: =('2025'!$H$55+'2025'!$H$59)/'2025'!$H$150 -> 0.60781543 | C28: =('2024'!$H$55+'2024'!$H$59)/'2024'!$H$149 -> 0.50804471
A30: Número de ações | B30: 683062222

Sheet DRE
A1: indicadores | B1: 2025 | C1: 2024 | D1: 2023
A2: receita líquida | B2: ='2025'!H176 -> 4564874 | C2: ='2024'!H175 -> 4108311 | D2: ='2023'!H197 -> 3734146
A3: Lucro Bruto | B3: ='2025'!H178 -> 2381646 | C3: ='2024'!H177 -> 1772696 | D3: ='2023'!H199 -> 1496215
A4: EBITDA = EBIT + Dep/Amort | B4: ='2025'!H187-'2025'!H285 -> 855531 | C4: ='2024'!H186-'2024'!H284 -> 301051 | D4: ='2023'!H209-'2023'!H309 -> -1777736
A5: EBIT | B5: ='2025'!H187 -> 594748 | C5: ='2024'!H186 -> 51236 | D5: ='2023'!H209 -> -1988986
A6: NOPAT = EBIT - IR/CSLL corrente | B6: ='2025'!H187-'2025'!H195 -> 537918 | C6: ='2024'!H186-'2024'!H194 -> 36777 | D6: ='2023'!H209-'2023'!H221 -> -1996176
